weekly_1/__init__.py
weekly_1/fish_ml.py
weekly_1/plot.py
weekly_1-0.2.7.dist-info/METADATA
weekly_1-0.2.7.dist-info/WHEEL
weekly_1-0.2.7.dist-info/entry_points.txt
weekly_1-0.2.7.dist-info/top_level.txt
weekly_1-0.2.7.dist-info/RECORD
