Metadata-Version: 2.1
Name: weekly_1
Version: 0.2.7
Summary: Weekly Project_Making a program that guess species of fish - Bream or Smelt
Author-email: EstherCho-7 <dkgkqm777@gmail.com>
License: MIT
Project-URL: Homepage, https://github.com/EstherCho-7/guess_fish
Project-URL: Issues, https://github.com/EstherCho-7/guess_fish/issues
Requires-Python: ==3.8.*
Requires-Dist: scikit-learn>=1.3.2
Requires-Dist: matplotlib>=3.7.5
